dateglob/__init__.py
dateglob/py.typed
dateglob-1.1.1.dist-info/LICENSE.txt
dateglob-1.1.1.dist-info/METADATA
dateglob-1.1.1.dist-info/WHEEL
dateglob-1.1.1.dist-info/top_level.txt
dateglob-1.1.1.dist-info/RECORD
