Metadata-Version: 2.1
Name: dateglob
Version: 1.1.1
Summary: Convert a set of dates into a compact list of globs
Home-page: http://github.com/Yelp/dateglob
Author: David Marin
Author-email: dm@davidmarin.org
License: Apache
Platform: UNKNOWN
Classifier: Development Status :: 4 - Beta
Classifier: Intended Audience :: Developers
Classifier: License :: OSI Approved :: Apache Software License
Classifier: Natural Language :: English
Classifier: Operating System :: OS Independent
Classifier: Programming Language :: Python
Classifier: Programming Language :: Python :: 3
Classifier: Programming Language :: Python :: 3.7
Classifier: Programming Language :: Python :: 3.8
Classifier: Topic :: Utilities
Requires-Python: >=3.7
